{
  "MATC": "MATIC",
  "ETH": "ETH",
  "BTC": "BTC",
  "DOGE": "DOGE",
  "USDC": "USDC",
  "XAU": "XAU",
  "XAG": "XAG",
  "USD": "USD",
  "GBP": "GBP",
  "CHF": "CHF",
  "EUR": "EUR",
  "JPY": "JPY",
  "stTH": "STETH",
  "stUS": "STUSD",
  "wstT": "WSTETH",
  "stER": "STEUR",
  "EURA": "EURA",
  "LUSD": "LUSD",
  "wETH": "WEETH",
  "OKB": "WOKB",
  "WIF": "WIF",
  "PEPE": "PEPE",
  "SOL": "SOL",
  "ZRO": "ZRO",
  "ETHf": "ETHFI",
  "ZK": "ZK",
  "PNDL": "PENDLE",
  "TR24": "TRUMP24",
  "BTLJ": "BTLJ"
}
